resto_client/__init__.py
resto_client/base_exceptions.py
resto_client/version.py
resto_client/cli/__init__.py
resto_client/cli/cli_utils.py
resto_client/cli/persistence.py
resto_client/cli/resto_client_cli.py
resto_client/cli/resto_client_parameters.py
resto_client/cli/resto_client_settings.py
resto_client/cli/resto_server_persisted.py
resto_client/cli/parser/__init__.py
resto_client/cli/parser/parser_common.py
resto_client/cli/parser/parser_configure_server.py
resto_client/cli/parser/parser_download.py
resto_client/cli/parser/parser_search.py
resto_client/cli/parser/parser_set.py
resto_client/cli/parser/parser_settings.py
resto_client/cli/parser/parser_show.py
resto_client/cli/parser/parser_unset.py
resto_client/cli/parser/resto_client_parser.py
resto_client/entities/__init__.py
resto_client/entities/resto_collection.py
resto_client/entities/resto_collections.py
resto_client/entities/resto_criteria.py
resto_client/entities/resto_criteria_definition.py
resto_client/entities/resto_feature.py
resto_client/entities/resto_feature_collection.py
resto_client/entities/resto_license.py
resto_client/entities/resto_statistics.py
resto_client/functions/__init__.py
resto_client/functions/aoi_utils.py
resto_client/functions/utils.py
resto_client/generic/__init__.py
resto_client/generic/basic_types.py
resto_client/generic/property_decoration.py
resto_client/generic/user_dirs.py
resto_client/requests/__init__.py
resto_client/requests/authentication_requests.py
resto_client/requests/authenticator.py
resto_client/requests/base_request.py
resto_client/requests/collections_requests.py
resto_client/requests/features_requests.py
resto_client/requests/resto_json_request.py
resto_client/requests/service_requests.py
resto_client/responses/__init__.py
resto_client/responses/authentication_responses.py
resto_client/responses/collection_description.py
resto_client/responses/collections_description.py
resto_client/responses/download_error_response.py
resto_client-0.5.0.dist-info/LICENSE
resto_client-0.5.0.dist-info/METADATA
resto_client-0.5.0.dist-info/WHEEL
resto_client-0.5.0.dist-info/entry_points.txt
resto_client-0.5.0.dist-info/top_level.txt
resto_client-0.5.0.dist-info/RECORD
