Metadata-Version: 2.1
Name: resto-client
Version: 0.5.0
Summary: Library and CLI interface for accessing resto servers
Home-page: https://github.com/CNES/resto_client
Author: Agwilh Collet, Alain Giros
Author-email: Agwilh.Collet@cnes.fr, Alain.Giros@cnes.fr
License: Apache 2
Keywords: resto,remote sensing,theia,peps,sentinel hub,creodias,kalideos,recovery observatory
Platform: any
Classifier: Development Status :: 3 - Alpha
Classifier: Intended Audience :: Developers
Classifier: Intended Audience :: End Users/Desktop
Classifier: Environment :: Console
Classifier: Topic :: Software Development :: Libraries :: Python Modules
Classifier: License :: OSI Approved :: Apache Software License
Classifier: Operating System :: OS Independent
Classifier: Programming Language :: Python
Classifier: Programming Language :: Python :: 3.6
Classifier: Programming Language :: Python :: 3.7
Classifier: Programming Language :: Python :: 3.8
Classifier: Typing :: Typed
Requires-Python: >=3.6
Requires-Dist: requests
Requires-Dist: tqdm
Requires-Dist: geojson
Requires-Dist: ptable
Requires-Dist: appdirs
Requires-Dist: shapely
Requires-Dist: colorama
